astroutils/__init__.py
astroutils/binning.py
astroutils/galactic.py
astroutils/plot_crt.py
astroutils-0.1.0.dist-info/METADATA
astroutils-0.1.0.dist-info/RECORD
astroutils-0.1.0.dist-info/WHEEL
astroutils-0.1.0.dist-info/top_level.txt
